KEC_BDA/__init__.py
KEC_BDA/exp2A.py
KEC_BDA/exp2B.py
KEC_BDA/exp3.py
KEC_BDA/exp4.py
KEC_BDA/exp5.py
KEC_BDA/exp6.py
KEC_BDA/exp7.py
KEC_BDA/exp8.py
KEC_BDA/main.py
KEC_BDA-0.1.0.dist-info/METADATA
KEC_BDA-0.1.0.dist-info/WHEEL
KEC_BDA-0.1.0.dist-info/top_level.txt
KEC_BDA-0.1.0.dist-info/RECORD
