Metadata-Version: 2.1
Name: KEC_BDA
Version: 0.1.0
Summary: A simple Python module that prints 'Hello, World!'
Author: TVK-VIJAY
Author-email: tvkvijay03@gmail.com
Classifier: Programming Language :: Python :: 3
Classifier: License :: OSI Approved :: MIT License
Classifier: Operating System :: OS Independent
Requires-Python: >=3.6
